README.md
setup.py
django_db_locks.egg-info/PKG-INFO
django_db_locks.egg-info/SOURCES.txt
django_db_locks.egg-info/dependency_links.txt
django_db_locks.egg-info/requires.txt
django_db_locks.egg-info/top_level.txt
locks/__init__.py
locks/admin.py
locks/apps.py
locks/decorators.py
locks/exceptions.py
locks/locks.py
locks/models.py
locks/router.py
locks/tests.py
locks/management/__init__.py
locks/management/commands/__init__.py
locks/management/commands/lock.py
locks/management/commands/unlock.py
locks/migrations/0001_initial.py
locks/migrations/0002_auto_20180316_1755.py
locks/migrations/0003_auto_20180316_1757.py
locks/migrations/__init__.py