Metadata-Version: 1.0
Name: django-db-locks
Version: 0.0.8
Summary: easy databaselocking for processes
Home-page: https://github.com/BlockHub/django-locks
Author: Charles
Author-email: karel@blockhub.nl
License: UNKNOWN
Platform: UNKNOWN
